opentimestamps/__init__.py
opentimestamps/bitcoin.py
opentimestamps/calendar.py
opentimestamps/timestamp.py
opentimestamps/core/__init__.py
opentimestamps/core/git.py
opentimestamps/core/log.py
opentimestamps/core/notary.py
opentimestamps/core/op.py
opentimestamps/core/packetstream.py
opentimestamps/core/serialize.py
opentimestamps/core/timestamp.py
opentimestamps/core/dubious/__init__.py
opentimestamps/core/dubious/notary.py
opentimestamps/tests/__init__.py
opentimestamps/tests/test_bitcoin.py
opentimestamps/tests/test_calendar.py
opentimestamps/tests/core/__init__.py
opentimestamps/tests/core/test_git.py
opentimestamps/tests/core/test_log.py
opentimestamps/tests/core/test_notary.py
opentimestamps/tests/core/test_op.py
opentimestamps/tests/core/test_packetstream.py
opentimestamps/tests/core/test_serialize.py
opentimestamps/tests/core/test_timestamp.py
opentimestamps/tests/core/dubious/__init__.py
opentimestamps/tests/core/dubious/test_notary.py
opentimestamps-0.4.5.dist-info/LICENSE
opentimestamps-0.4.5.dist-info/METADATA
opentimestamps-0.4.5.dist-info/WHEEL
opentimestamps-0.4.5.dist-info/top_level.txt
opentimestamps-0.4.5.dist-info/RECORD
