Metadata-Version: 2.1
Name: opentimestamps
Version: 0.4.5
Summary: Create and verify OpenTimestamps proofs
Home-page: https://github.com/opentimestamps/python-opentimestamps
Author: Peter Todd
Author-email: pete@petertodd.org
License: LGPL3
Keywords: cryptography timestamping bitcoin
Platform: UNKNOWN
Classifier: Development Status :: 4 - Beta
Classifier: Intended Audience :: Developers
Classifier: Topic :: Security :: Cryptography
Classifier: License :: OSI Approved :: GNU Lesser General Public License v3 or later (LGPLv3+)
Classifier: Programming Language :: Python :: 3 :: Only
